certora_cli/__init__.py
certora_cli/certoraRun.py
certora_cli/EVMVerifier/__init__.py
certora_cli/EVMVerifier/certoraBuild.py
certora_cli/EVMVerifier/certoraCloudIO.py
certora_cli/EVMVerifier/certoraCollectRunMetadata.py
certora_cli/EVMVerifier/certoraConfigIO.py
certora_cli/EVMVerifier/certoraDualArg.py
certora_cli/EVMVerifier/certoraJobList.py
certora_cli/EVMVerifier/certoraNodeFilters.py
certora_cli/EVMVerifier/certoraType.py
certora_cli/EVMVerifier/Compiler/CompilerCollector.py
certora_cli/EVMVerifier/Compiler/CompilerCollectorSol.py
certora_cli/EVMVerifier/Compiler/CompilerCollectorVy.py
certora_cli/EVMVerifier/Compiler/__init__.py
certora_cli/Shared/__init__.py
certora_cli/Shared/certoraLogging.py
certora_cli/Shared/certoraTester.py
certora_cli/Shared/certoraUtils.py
certora_jars/Typechecker.jar
certora_jars/__init__.py
certora_cli_alpha_Eyal_CompilerCollector-20220725.16.31.dist-info/LICENSE
certora_cli_alpha_Eyal_CompilerCollector-20220725.16.31.dist-info/METADATA
certora_cli_alpha_Eyal_CompilerCollector-20220725.16.31.dist-info/WHEEL
certora_cli_alpha_Eyal_CompilerCollector-20220725.16.31.dist-info/entry_points.txt
certora_cli_alpha_Eyal_CompilerCollector-20220725.16.31.dist-info/top_level.txt
certora_cli_alpha_Eyal_CompilerCollector-20220725.16.31.dist-info/RECORD
